LICENSE
MANIFEST.in
README.md
setup.py
django_memento_framework.egg-info/PKG-INFO
django_memento_framework.egg-info/SOURCES.txt
django_memento_framework.egg-info/dependency_links.txt
django_memento_framework.egg-info/not-zip-safe
django_memento_framework.egg-info/requires.txt
django_memento_framework.egg-info/top_level.txt
memento/__init__.py
memento/tests.py
memento/templates/memento/timemap/link_index.txt
memento/templates/memento/timemap/link_list.txt
memento/templatetags/__init__.py
memento/templatetags/memento_tags.py
memento/timegate/__init__.py
memento/timegate/views.py
memento/timemap/__init__.py
memento/timemap/feedgenerator.py