Metadata-Version: 1.0
Name: django-memento-framework
Version: 0.0.3
Summary: A set for helpers for Django web sites to enable the Memento framework for time-based access
Home-page: http://django-memento-framework.readthedocs.org
Author: Ben Welsh
Author-email: ben.welsh@gmail.com
License: UNKNOWN
Platform: UNKNOWN
